noxcollections/__init__.py
noxcollections/lists.py
noxcollections/py.typed
noxcollections/stack.py
noxcollections-0.1.0.dist-info/LICENSE
noxcollections-0.1.0.dist-info/WHEEL
noxcollections-0.1.0.dist-info/METADATA
noxcollections-0.1.0.dist-info/RECORD
