Metadata-Version: 2.1
Name: noxcollections
Version: 0.1.0
Summary: Pure python implementation of simple data structures and some basic algorithms focused on readability.
Home-page: https://github.com/NoxMar/noxcollections
License: MIT
Keywords: data-structure,collection,algorithm
Author: Marcin Śladewski
Author-email: mar4sladewski@gmail.com
Requires-Python: >=3.8,<4.0
Classifier: License :: OSI Approved :: MIT License
Classifier: Programming Language :: Python :: 3
Classifier: Programming Language :: Python :: 3.10
Classifier: Programming Language :: Python :: 3.8
Classifier: Programming Language :: Python :: 3.9
Project-URL: Repository, https://github.com/NoxMar/noxcollections
